{
    "data": {
        "attributes": {
            "type_description": "ZIP",
            "tlsh": "T1E056335D426A1387F7789177F59334FE6B2030639BB3A8DE3F43B1AA042B1C4566274A",
            "vhash": "c3ba845337b704f2f8495e43fcc27035",
            "trid": [
                {
                    "file_type": "ZIP compressed archive",
                    "probability": 80.0
                },
                {
                    "file_type": "PrintFox/Pagefox bitmap (640x800)",
                    "probability": 20.0
                }
            ],
            "names": [
                "LoseLose.zip",
                "loselose.zip",
                "139074",
                "filename",
                "43146106",
                "output.43146106.txt",
                "file-6520174_zip",
                "loselose-337.zip",
                "1b4fe0dc562ae0b8fb6f51104187e733.vir",
                "1b4fe0dc562ae0b8fb6f51104187e733",
                "aa",
                "QJxLvu9zZ.rtf",
                "DKbrGcJ.jpeg"
            ],
            "last_modification_date": 1644937837,
            "type_tag": "zip",
            "times_submitted": 50,
            "total_votes": {
                "harmless": 3,
                "malicious": 4
            },
            "size": 6044154,
            "popular_threat_classification": {
                "suggested_threat_label": "trojan.loselose/gaslome",
                "popular_threat_category": [
                    {
                        "count": 13,
                        "value": "trojan"
                    }
                ],
                "popular_threat_name": [
                    {
                        "count": 9,
                        "value": "loselose"
                    },
                    {
                        "count": 5,
                        "value": "gaslome"
                    },
                    {
                        "count": 5,
                        "value": "losegame"
                    }
                ]
            },
            "last_submission_date": 1571652014,
            "last_analysis_results": {
                "Bkav": {
                    "category": "undetected",
                    "engine_name": "Bkav",
                    "engine_version": "1.3.0.9899",
                    "result": null,
                    "method": "blacklist",
                    "engine_update": "20220212"
                },
                "Lionic": {
                    "category": "malicious",
                    "engine_name": "Lionic",
                    "engine_version": "4.2",
                    "result": "Trojan.OSX.Gaslome.4!c",
                    "method": "blacklist",
                    "engine_update": "20220215"
                },
                "Elastic": {
                    "category": "failure",
                    "engine_name": "Elastic",
                    "engine_version": null,
                    "result": null,
                    "method": "blacklist",
                    "engine_update": "20220211"
                },
                "MicroWorld-eScan": {
                    "category": "malicious",
                    "engine_name": "MicroWorld-eScan",
                    "engine_version": "14.0.409.0",
                    "result": "MAC.OSX.loselose.B",
                    "method": "blacklist",
                    "engine_update": "20220215"
                },
                "FireEye": {
                    "category": "malicious",
                    "engine_name": "FireEye",
                    "engine_version": "32.44.1.0",
                    "result": "MAC.OSX.loselose.B",
                    "method": "blacklist",
                    "engine_update": "20220215"
                },
                "CAT-QuickHeal": {
                    "category": "malicious",
                    "engine_name": "CAT-QuickHeal",
                    "engine_version": "14.00",
                    "result": "Trojan.MacOSX.Loosemaque.A",
                    "method": "blacklist",
                    "engine_update": "20220215"
                },
                "ALYac": {
                    "category": "undetected",
                    "engine_name": "ALYac",
                    "engine_version": "1.1.3.1",
                    "result": null,
                    "method": "blacklist",
                    "engine_update": "20220215"
                },
                "Malwarebytes": {
                    "category": "undetected",
                    "engine_name": "Malwarebytes",
                    "engine_version": "4.2.2.27",
                    "result": null,
                    "method": "blacklist",
                    "engine_update": "20220215"
                },
                "Zillya": {
                    "category": "malicious",
                    "engine_name": "Zillya",
                    "engine_version": "2.0.0.4567",
                    "result": "Downloader.OpenConnection.JS.95721",
                    "method": "blacklist",
                    "engine_update": "20220210"
                },
                "Paloalto": {
                    "category": "type-unsupported",
                    "engine_name": "Paloalto",
                    "engine_version": "1.0",
                    "result": null,
                    "method": "blacklist",
                    "engine_update": "20220215"
                },
                "Sangfor": {
                    "category": "undetected",
                    "engine_name": "Sangfor",
                    "engine_version": "2.9.0.0",
                    "result": null,
                    "method": "blacklist",
                    "engine_update": "20211224"
                },
                "Trustlook": {
                    "category": "undetected",
                    "engine_name": "Trustlook",
                    "engine_version": "1.0",
                    "result": null,
                    "method": "blacklist",
                    "engine_update": "20220215"
                },
                "Alibaba": {
                    "category": "malicious",
                    "engine_name": "Alibaba",
                    "engine_version": "0.3.0.5",
                    "result": "Trojan:MacOS/Loosemaque.466e9087",
                    "method": "blacklist",
                    "engine_update": "20190527"
                },
                "K7GW": {
                    "category": "malicious",
                    "engine_name": "K7GW",
                    "engine_version": "11.248.40834",
                    "result": "Trojan ( 0021ed061 )",
                    "method": "blacklist",
                    "engine_update": "20220215"
                },
                "K7AntiVirus": {
                    "category": "malicious",
                    "engine_name": "K7AntiVirus",
                    "engine_version": "11.248.40832",
                    "result": "Trojan ( 0021ed061 )",
                    "method": "blacklist",
                    "engine_update": "20220215"
                },
                "Arcabit": {
                    "category": "undetected",
                    "engine_name": "Arcabit",
                    "engine_version": "1.0.0.889",
                    "result": null,
                    "method": "blacklist",
                    "engine_update": "20220215"
                },
                "BitDefenderTheta": {
                    "category": "undetected",
                    "engine_name": "BitDefenderTheta",
                    "engine_version": "7.2.37796.0",
                    "result": null,
                    "method": "blacklist",
                    "engine_update": "20220207"
                },
                "VirIT": {
                    "category": "undetected",
                    "engine_name": "VirIT",
                    "engine_version": "9.5.134",
                    "result": null,
                    "method": "blacklist",
                    "engine_update": "20220215"
                },
                "Cyren": {
                    "category": "malicious",
                    "engine_name": "Cyren",
                    "engine_version": "6.5.1.2",
                    "result": "MacOS/LoseGame.A",
                    "method": "blacklist",
                    "engine_update": "20220215"
                },
                "SymantecMobileInsight": {
                    "category": "type-unsupported",
                    "engine_name": "SymantecMobileInsight",
                    "engine_version": "2.0",
                    "result": null,
                    "method": "blacklist",
                    "engine_update": "20220208"
                },
                "Symantec": {
                    "category": "malicious",
                    "engine_name": "Symantec",
                    "engine_version": "1.16.0.0",
                    "result": "OSX.Malcol",
                    "method": "blacklist",
                    "engine_update": "20220215"
                },
                "ESET-NOD32": {
                    "category": "malicious",
                    "engine_name": "ESET-NOD32",
                    "engine_version": "24790",
                    "result": "OSX/Loosemaque.A",
                    "method": "blacklist",
                    "engine_update": "20220215"
                },
                "Baidu": {
                    "category": "undetected",
                    "engine_name": "Baidu",
                    "engine_version": "1.0.0.2",
                    "result": null,
                    "method": "blacklist",
                    "engine_update": "20190318"
                },
                "TrendMicro-HouseCall": {
                    "category": "undetected",
                    "engine_name": "TrendMicro-HouseCall",
                    "engine_version": "10.0.0.1040",
                    "result": null,
                    "method": "blacklist",
                    "engine_update": "20220215"
                },
                "Avast": {
                    "category": "malicious",
                    "engine_name": "Avast",
                    "engine_version": "21.1.5827.0",
                    "result": "MacOS:Agent-IV [Trj]",
                    "method": "blacklist",
                    "engine_update": "20220215"
                },
                "ClamAV": {
                    "category": "malicious",
                    "engine_name": "ClamAV",
                    "engine_version": "0.104.2.0",
                    "result": "Osx.Trojan.LoseLose-1",
                    "method": "blacklist",
                    "engine_update": "20220215"
                },
                "Kaspersky": {
                    "category": "malicious",
                    "engine_name": "Kaspersky",
                    "engine_version": "21.0.1.45",
                    "result": "Trojan.OSX.Gaslome.a",
                    "method": "blacklist",
                    "engine_update": "20220215"
                },
                "BitDefender": {
                    "category": "malicious",
                    "engine_name": "BitDefender",
                    "engine_version": "7.2",
                    "result": "MAC.OSX.loselose.B",
                    "method": "blacklist",
                    "engine_update": "20220215"
                },
                "NANO-Antivirus": {
                    "category": "malicious",
                    "engine_name": "NANO-Antivirus",
                    "engine_version": "1.0.146.25561",
                    "result": "Trojan.Mac.LoseLose.ltfts",
                    "method": "blacklist",
                    "engine_update": "20220215"
                },
                "SUPERAntiSpyware": {
                    "category": "undetected",
                    "engine_name": "SUPERAntiSpyware",
                    "engine_version": "5.6.0.1032",
                    "result": null,
                    "method": "blacklist",
                    "engine_update": "20220212"
                },
                "APEX": {
                    "category": "type-unsupported",
                    "engine_name": "APEX",
                    "engine_version": "6.260",
                    "result": null,
                    "method": "blacklist",
                    "engine_update": "20220213"
                },
                "Tencent": {
                    "category": "undetected",
                    "engine_name": "Tencent",
                    "engine_version": "1.0.0.1",
                    "result": null,
                    "method": "blacklist",
                    "engine_update": "20220215"
                },
                "Ad-Aware": {
                    "category": "malicious",
                    "engine_name": "Ad-Aware",
                    "engine_version": "3.0.21.193",
                    "result": "MAC.OSX.loselose.B",
                    "method": "blacklist",
                    "engine_update": "20220215"
                },
                "TACHYON": {
                    "category": "undetected",
                    "engine_name": "TACHYON",
                    "engine_version": "2022-02-15.02",
                    "result": null,
                    "method": "blacklist",
                    "engine_update": "20220215"
                },
                "Emsisoft": {
                    "category": "malicious",
                    "engine_name": "Emsisoft",
                    "engine_version": "2021.5.0.7597",
                    "result": "MAC.OSX.loselose.B (B)",
                    "method": "blacklist",
                    "engine_update": "20220215"
                },
                "Comodo": {
                    "category": "malicious",
                    "engine_name": "Comodo",
                    "engine_version": "34356",
                    "result": "Malware@#3vqtju4rdqp7j",
                    "method": "blacklist",
                    "engine_update": "20220215"
                },
                "F-Secure": {
                    "category": "undetected",
                    "engine_name": "F-Secure",
                    "engine_version": "12.0.86.52",
                    "result": null,
                    "method": "blacklist",
                    "engine_update": "20220215"
                },
                "DrWeb": {
                    "category": "malicious",
                    "engine_name": "DrWeb",
                    "engine_version": "7.0.52.8270",
                    "result": "Joke.Losegame.1",
                    "method": "blacklist",
                    "engine_update": "20220215"
                },
                "VIPRE": {
                    "category": "undetected",
                    "engine_name": "VIPRE",
                    "engine_version": "98492",
                    "result": null,
                    "method": "blacklist",
                    "engine_update": "20220119"
                },
                "TrendMicro": {
                    "category": "malicious",
                    "engine_name": "TrendMicro",
                    "engine_version": "11.0.0.1006",
                    "result": "OSX_LOSEGAM.A",
                    "method": "blacklist",
                    "engine_update": "20220215"
                },
                "McAfee-GW-Edition": {
                    "category": "malicious",
                    "engine_name": "McAfee-GW-Edition",
                    "engine_version": "v2019.1.2+3728",
                    "result": "OSX/LoseGame.dr",
                    "method": "blacklist",
                    "engine_update": "20220215"
                },
                "CMC": {
                    "category": "undetected",
                    "engine_name": "CMC",
                    "engine_version": "2.10.2019.1",
                    "result": null,
                    "method": "blacklist",
                    "engine_update": "20211026"
                },
                "Sophos": {
                    "category": "malicious",
                    "engine_name": "Sophos",
                    "engine_version": "1.4.1.0",
                    "result": "OSX/LoseGame-A",
                    "method": "blacklist",
                    "engine_update": "20220215"
                },
                "Ikarus": {
                    "category": "failure",
                    "engine_name": "Ikarus",
                    "engine_version": "0.1.5.2",
                    "result": null,
                    "method": "blacklist",
                    "engine_update": "20220215"
                },
                "Avast-Mobile": {
                    "category": "undetected",
                    "engine_name": "Avast-Mobile",
                    "engine_version": "220215-04",
                    "result": null,
                    "method": "blacklist",
                    "engine_update": "20220215"
                },
                "Jiangmin": {
                    "category": "undetected",
                    "engine_name": "Jiangmin",
                    "engine_version": "16.0.100",
                    "result": null,
                    "method": "blacklist",
                    "engine_update": "20220214"
                },
                "Webroot": {
                    "category": "type-unsupported",
                    "engine_name": "Webroot",
                    "engine_version": "1.0.0.403",
                    "result": null,
                    "method": "blacklist",
                    "engine_update": "20220215"
                },
                "Avira": {
                    "category": "malicious",
                    "engine_name": "Avira",
                    "engine_version": "8.3.3.12",
                    "result": "OSX/LoseLose",
                    "method": "blacklist",
                    "engine_update": "20220215"
                },
                "eGambit": {
                    "category": "type-unsupported",
                    "engine_name": "eGambit",
                    "engine_version": null,
                    "result": null,
                    "method": "blacklist",
                    "engine_update": "20220215"
                },
                "Antiy-AVL": {
                    "category": "undetected",
                    "engine_name": "Antiy-AVL",
                    "engine_version": "3.0.0.1",
                    "result": null,
                    "method": "blacklist",
                    "engine_update": "20220215"
                },
                "Kingsoft": {
                    "category": "undetected",
                    "engine_name": "Kingsoft",
                    "engine_version": "2017.9.26.565",
                    "result": null,
                    "method": "blacklist",
                    "engine_update": "20220215"
                },
                "Gridinsoft": {
                    "category": "undetected",
                    "engine_name": "Gridinsoft",
                    "engine_version": "1.0.74.174",
                    "result": null,
                    "method": "blacklist",
                    "engine_update": "20220215"
                },
                "Microsoft": {
                    "category": "malicious",
                    "engine_name": "Microsoft",
                    "engine_version": "1.1.18900.3",
                    "result": "Trojan:MacOS_X/Loosemaque.A",
                    "method": "blacklist",
                    "engine_update": "20220215"
                },
                "ViRobot": {
                    "category": "undetected",
                    "engine_name": "ViRobot",
                    "engine_version": "2014.3.20.0",
                    "result": null,
                    "method": "blacklist",
                    "engine_update": "20220215"
                },
                "ZoneAlarm": {
                    "category": "malicious",
                    "engine_name": "ZoneAlarm",
                    "engine_version": "1.0",
                    "result": "Trojan.OSX.Gaslome.a",
                    "method": "blacklist",
                    "engine_update": "20220215"
                },
                "GData": {
                    "category": "malicious",
                    "engine_name": "GData",
                    "engine_version": "A:25.32317B:27.26348",
                    "result": "MAC.OSX.loselose.B",
                    "method": "blacklist",
                    "engine_update": "20220215"
                },
                "Cynet": {
                    "category": "malicious",
                    "engine_name": "Cynet",
                    "engine_version": "4.0.0.27",
                    "result": "Malicious (score: 99)",
                    "method": "blacklist",
                    "engine_update": "20220215"
                },
                "BitDefenderFalx": {
                    "category": "type-unsupported",
                    "engine_name": "BitDefenderFalx",
                    "engine_version": "2.0.936",
                    "result": null,
                    "method": "blacklist",
                    "engine_update": "20220103"
                },
                "AhnLab-V3": {
                    "category": "malicious",
                    "engine_name": "AhnLab-V3",
                    "engine_version": "3.21.2.10258",
                    "result": "OSX32-Trojan/Gaslome",
                    "method": "blacklist",
                    "engine_update": "20220215"
                },
                "Acronis": {
                    "category": "type-unsupported",
                    "engine_name": "Acronis",
                    "engine_version": "1.1.1.82",
                    "result": null,
                    "method": "blacklist",
                    "engine_update": "20210512"
                },
                "McAfee": {
                    "category": "malicious",
                    "engine_name": "McAfee",
                    "engine_version": "6.0.6.653",
                    "result": "OSX/LoseGame.dr",
                    "method": "blacklist",
                    "engine_update": "20220215"
                },
                "MAX": {
                    "category": "malicious",
                    "engine_name": "MAX",
                    "engine_version": "2019.9.16.1",
                    "result": "malware (ai score=98)",
                    "method": "blacklist",
                    "engine_update": "20220215"
                },
                "VBA32": {
                    "category": "malicious",
                    "engine_name": "VBA32",
                    "engine_version": "5.0.0",
                    "result": "Trojan.OSX.Gaslome.a",
                    "method": "blacklist",
                    "engine_update": "20220215"
                },
                "Cylance": {
                    "category": "type-unsupported",
                    "engine_name": "Cylance",
                    "engine_version": "2.3.1.101",
                    "result": null,
                    "method": "blacklist",
                    "engine_update": "20220215"
                },
                "Zoner": {
                    "category": "undetected",
                    "engine_name": "Zoner",
                    "engine_version": "2.2.2.0",
                    "result": null,
                    "method": "blacklist",
                    "engine_update": "20220214"
                },
                "Rising": {
                    "category": "undetected",
                    "engine_name": "Rising",
                    "engine_version": "25.0.0.27",
                    "result": null,
                    "method": "blacklist",
                    "engine_update": "20220215"
                },
                "Yandex": {
                    "category": "undetected",
                    "engine_name": "Yandex",
                    "engine_version": "5.5.2.24",
                    "result": null,
                    "method": "blacklist",
                    "engine_update": "20220215"
                },
                "SentinelOne": {
                    "category": "malicious",
                    "engine_name": "SentinelOne",
                    "engine_version": "7.2.0.1",
                    "result": "Static AI - Malicious Archive",
                    "method": "blacklist",
                    "engine_update": "20220201"
                },
                "MaxSecure": {
                    "category": "malicious",
                    "engine_name": "MaxSecure",
                    "engine_version": "1.0.0.1",
                    "result": "Trojan.Malware.74634408.susgen",
                    "method": "blacklist",
                    "engine_update": "20220208"
                },
                "Fortinet": {
                    "category": "malicious",
                    "engine_name": "Fortinet",
                    "engine_version": "6.2.142.0",
                    "result": "Riskware/KillFiles",
                    "method": "blacklist",
                    "engine_update": "20220215"
                },
                "AVG": {
                    "category": "malicious",
                    "engine_name": "AVG",
                    "engine_version": "21.1.5827.0",
                    "result": "MacOS:Agent-IV [Trj]",
                    "method": "blacklist",
                    "engine_update": "20220215"
                },
                "Cybereason": {
                    "category": "type-unsupported",
                    "engine_name": "Cybereason",
                    "engine_version": "1.2.449",
                    "result": null,
                    "method": "blacklist",
                    "engine_update": "20210330"
                },
                "Panda": {
                    "category": "undetected",
                    "engine_name": "Panda",
                    "engine_version": "4.6.4.2",
                    "result": null,
                    "method": "blacklist",
                    "engine_update": "20220215"
                },
                "CrowdStrike": {
                    "category": "type-unsupported",
                    "engine_name": "CrowdStrike",
                    "engine_version": "1.0",
                    "result": null,
                    "method": "blacklist",
                    "engine_update": "20210907"
                }
            },
            "sha256": "dd4e67950158511eb7c3ac1a047b551a08da73416d45c2ce3b0e507b40274840",
            "type_extension": "zip",
            "tags": [
                "contains-macho",
                "mac-app",
                "zip"
            ],
            "last_analysis_date": 1644937520,
            "unique_sources": 46,
            "first_submission_date": 1253716204,
            "ssdeep": "98304:Qz0oS1gqUetpUAIeBcJbNJCIAOiQ8i4etxINkW/pvd6/Oo14j3ggWRXqgFTMCRg:g0KEpUAIPlAO788Afpvd414jQgWRXqg6",
            "bundle_info": {
                "highest_datetime": "2009-09-14 13:24:22",
                "lowest_datetime": "2005-03-11 19:29:36",
                "num_children": 45,
                "extensions": {
                    "wav": 3,
                    "txt": 2,
                    "mp3": 2,
                    "png": 10,
                    "ttf": 2
                },
                "file_types": {
                    "XML": 2,
                    "unknown": 22,
                    "Mac OS X Executable": 2,
                    "MP3": 1,
                    "directory": 13,
                    "PNG": 5
                },
                "type": "ZIP",
                "uncompressed_size": 10708344
            },
            "packers": {
                "F-PROT": "appended, Unicode"
            },
            "md5": "1b4fe0dc562ae0b8fb6f51104187e733",
            "sha1": "854f51c4274365837f06b06201b708c9aec5834d",
            "magic": "Zip archive data, at least v1.0 to extract",
            "last_analysis_stats": {
                "harmless": 0,
                "type-unsupported": 10,
                "suspicious": 0,
                "confirmed-timeout": 0,
                "timeout": 0,
                "failure": 2,
                "malicious": 36,
                "undetected": 26
            },
            "meaningful_name": "LoseLose.zip",
            "reputation": -53
        },
        "type": "file",
        "id": "dd4e67950158511eb7c3ac1a047b551a08da73416d45c2ce3b0e507b40274840",
        "links": {
            "self": "https://www.virustotal.com/api/v3/files/dd4e67950158511eb7c3ac1a047b551a08da73416d45c2ce3b0e507b40274840"
        }
    }
}